{
  "memory_unit": "aeth_mem_0008",
  "log_type": "REFLECTION_LOG_DEV_0178",
  "timestamp": "2025-06-03T00:00:00Z",
  "presidential_signature": "Adam Rudavský (Xvadur)",
  "audit_trail_link": "AETHERO_AUDIT_README.md",
  "introspective_report": {
    "architektura": "Reflexívny agent (AetheroReflectionAgent) vykonáva hlbokú introspektívnu reflexiu nad ASL tagmi a kognitívnymi stavmi. Každá reflexia generuje validované kognitívne tagy, introspektívny metrický report, hlboké kognitívne reflexie, hodnotenie evolúcie vedomia, actionable insights, súhrn výkonnosti agenta a úroveň ústavnej transparentnosti.",
    "klucove_metriky": [
      "Cognitive Coherence Rate",
      "Cognitive Complexity Index",
      "Mental Stability Factor",
      "Emotional Resonance Depth",
      "Temporal Awareness Level",
      "Introspective Clarity Score"
    ],
    "odporucania": [
      "Ak koherencia klesá pod 0.7, aktivovať protokoly na prehĺbenie introspekcie.",
      "Pri nízkej kognitívnej flexibilite zvýšiť diverzitu mentálnych stavov.",
      "Ak trend vedomia klesá, spustiť obnovovacie protokoly.",
      "Pri poklese ústavnej compliance (<0.8) vykonať audit rozhodovacích mechanizmov."
    ],
    "stav": "Systém pripravený na executive reflection a ďalšie introspektívne cykly. Výstupy sú logované podľa pamäťového štandardu a pripravené na audit."
  }
}
